README.md
setup.py
pcoinpay/__init__.py
pcoinpay/client.py
pcoinpay/crypto.py
pcoinpay_python.egg-info/PKG-INFO
pcoinpay_python.egg-info/SOURCES.txt
pcoinpay_python.egg-info/dependency_links.txt
pcoinpay_python.egg-info/requires.txt
pcoinpay_python.egg-info/top_level.txt